red_utils/__init__.py
red_utils/core/__init__.py
red_utils/core/constants.py
red_utils/core/dataclass_utils/__init__.py
red_utils/core/dataclass_utils/mixins/__init__.py
red_utils/core/dataclass_utils/mixins/mixin_classes.py
red_utils/domain/__init__.py
red_utils/exc/__init__.py
red_utils/exc/_generic.py
red_utils/exc/base.py
red_utils/exc/import_exc/__init__.py
red_utils/exc/import_exc/_import.py
red_utils/ext/__init__.py
red_utils/ext/context_managers/__init__.py
red_utils/ext/context_managers/cli_spinners/__init__.py
red_utils/ext/context_managers/cli_spinners/handlers.py
red_utils/ext/dataframe_utils/__init__.py
red_utils/ext/dataframe_utils/pandas_utils/__init__.py
red_utils/ext/dataframe_utils/pandas_utils/constants.py
red_utils/ext/dataframe_utils/pandas_utils/operations.py
red_utils/ext/dataframe_utils/polars_utils/__init__.py
red_utils/ext/dataframe_utils/validators/__init__.py
red_utils/ext/dataframe_utils/validators/pandas_validators/__init__.py
red_utils/ext/dataframe_utils/validators/pandas_validators/validators.py
red_utils/ext/diskcache_utils/__defaults.py
red_utils/ext/diskcache_utils/__init__.py
red_utils/ext/diskcache_utils/__methods.py
red_utils/ext/diskcache_utils/classes.py
red_utils/ext/diskcache_utils/constants.py
red_utils/ext/diskcache_utils/validators.py
red_utils/ext/diskcache_utils/controllers/__init__.py
red_utils/ext/diskcache_utils/controllers/_controller.py
red_utils/ext/fastapi_utils/__init__.py
red_utils/ext/fastapi_utils/constants.py
red_utils/ext/fastapi_utils/dependencies.py
red_utils/ext/fastapi_utils/healthcheck.py
red_utils/ext/fastapi_utils/operations.py
red_utils/ext/fastapi_utils/tag_definitions.py
red_utils/ext/fastapi_utils/uvicorn_override.py
red_utils/ext/fastapi_utils/validators.py
red_utils/ext/httpx_utils/__init__.py
red_utils/ext/httpx_utils/classes.py
red_utils/ext/httpx_utils/constants.py
red_utils/ext/httpx_utils/operations.py
red_utils/ext/httpx_utils/validators.py
red_utils-0.2.25.dist-info/METADATA
red_utils-0.2.25.dist-info/WHEEL
red_utils-0.2.25.dist-info/top_level.txt
red_utils-0.2.25.dist-info/RECORD
