Metadata-Version: 2.1
Name: red_utils
Version: 0.2.25
Summary: Collection of utility scripts/functions that I use frequently.
Author-email: redjax <none@none.com>, redjax <jackenyon@gmail.com>
License: MIT
Project-URL: Repository, https://github.com/redjax/red-utils
Project-URL: Documentation, https://red-utils.readthedocs.io/en/latest/
Project-URL: Download, https://pypi.org/project/red_utils/
Requires-Python: >=3.11
Provides-Extra: all
Requires-Dist: diskcache >=5.6.3 ; extra == 'all'
Requires-Dist: fastapi >=0.109.2 ; extra == 'all'
Requires-Dist: uvicorn >=0.27.1 ; extra == 'all'
Requires-Dist: loguru >=0.7.2 ; extra == 'all'
Requires-Dist: httpx >=0.26.0 ; extra == 'all'
Requires-Dist: msgpack >=1.0.7 ; extra == 'all'
Requires-Dist: pendulum >=3.0.0 ; extra == 'all'
Requires-Dist: sqlalchemy >=2.0.25 ; extra == 'all'
Requires-Dist: pandas >=2.1.4 ; extra == 'all'
Requires-Dist: fastparquet >=2024.2.0 ; extra == 'all'
Requires-Dist: pyarrow >=15.0.0 ; extra == 'all'
Requires-Dist: ipykernel >=6.29.2 ; extra == 'all'
Requires-Dist: hishel >=0.0.26 ; extra == 'all'
Requires-Dist: chardet >=5.2.0 ; extra == 'all'
Requires-Dist: rich >=13.7.1 ; extra == 'all'
Provides-Extra: ci
Requires-Dist: ruff >=0.1.13 ; extra == 'ci'
Requires-Dist: black >=23.12.1 ; extra == 'ci'
Requires-Dist: pytest >=7.4.4 ; extra == 'ci'
Requires-Dist: nox >=2023.4.22 ; extra == 'ci'
Provides-Extra: data
Requires-Dist: ipykernel >=6.28.0 ; extra == 'data'
Requires-Dist: pandas >=2.1.4 ; extra == 'data'
Requires-Dist: fastparquet >=2023.10.1 ; extra == 'data'
Provides-Extra: dataframes
Requires-Dist: pandas >=2.1.4 ; extra == 'dataframes'
Requires-Dist: fastparquet >=2023.10.1 ; extra == 'dataframes'
Requires-Dist: pyarrow >=15.0.0 ; extra == 'dataframes'
Provides-Extra: docs
Requires-Dist: pygments >=2.17.2 ; extra == 'docs'
Requires-Dist: mkdocs >=1.5.3 ; extra == 'docs'
Requires-Dist: mkdocs-material >=9.5.4 ; extra == 'docs'
Requires-Dist: mkdocstrings[python] >=0.24.0 ; extra == 'docs'
Requires-Dist: markdown-include >=0.8.1 ; extra == 'docs'
Requires-Dist: mkdocs-gen-files >=0.5.0 ; extra == 'docs'
Requires-Dist: mkdocs-autorefs >=0.5.0 ; extra == 'docs'
Requires-Dist: mkdocs-section-index >=0.3.8 ; extra == 'docs'
Requires-Dist: mkdocs-literate-nav >=0.6.1 ; extra == 'docs'
Provides-Extra: fastapi
Requires-Dist: fastapi >=0.109.0 ; extra == 'fastapi'
Requires-Dist: sqlalchemy >=2.0.25 ; extra == 'fastapi'
Requires-Dist: loguru >=0.7.2 ; extra == 'fastapi'
Requires-Dist: httpx >=0.26.0 ; extra == 'fastapi'
Requires-Dist: msgpack >=1.0.7 ; extra == 'fastapi'
Requires-Dist: uvicorn >=0.25.0 ; extra == 'fastapi'
Requires-Dist: pendulum >=3.0.0 ; extra == 'fastapi'
Provides-Extra: http
Requires-Dist: httpx >=0.26.0 ; extra == 'http'
Requires-Dist: diskcache >=5.6.3 ; extra == 'http'
Requires-Dist: loguru >=0.7.2 ; extra == 'http'
Requires-Dist: pendulum >=3.0.0 ; extra == 'http'
Requires-Dist: msgpack >=1.0.7 ; extra == 'http'
Requires-Dist: pendulum >=2.1.2 ; extra == 'http'
Requires-Dist: hishel >=0.0.26 ; extra == 'http'
Requires-Dist: chardet >=5.2.0 ; extra == 'http'
Provides-Extra: standard
Requires-Dist: diskcache >=5.6.3 ; extra == 'standard'
Requires-Dist: loguru >=0.7.2 ; extra == 'standard'
Requires-Dist: httpx >=0.26.0 ; extra == 'standard'
Requires-Dist: pendulum >=3.0.0 ; extra == 'standard'
Requires-Dist: rich >=13.7.0 ; extra == 'standard'
Requires-Dist: msgpack >=1.0.7 ; extra == 'standard'
Requires-Dist: sqlalchemy >=2.0.25 ; extra == 'standard'
Requires-Dist: chardet >=5.2.0 ; extra == 'standard'
Requires-Dist: hishel >=0.0.26 ; extra == 'standard'
Provides-Extra: tests
Requires-Dist: loguru >=0.7.2 ; extra == 'tests'
Requires-Dist: httpx >=0.27.0 ; extra == 'tests'
Requires-Dist: hishel >=0.0.26 ; extra == 'tests'
Requires-Dist: chardet >=5.2.0 ; extra == 'tests'
Requires-Dist: sqlalchemy >=2.0.30 ; extra == 'tests'
Requires-Dist: pendulum >=3.0.0 ; extra == 'tests'
Requires-Dist: pytest-xdist >=3.6.1 ; extra == 'tests'
